whirr/__init__.py
whirr/client.py
whirr/config.py
whirr/db.py
whirr/run.py
whirr/runner.py
whirr/sweep.py
whirr/system_metrics.py
whirr/ablate/__init__.py
whirr/ablate/models.py
whirr/cli/__init__.py
whirr/cli/cancel.py
whirr/cli/compare.py
whirr/cli/dashboard.py
whirr/cli/doctor.py
whirr/cli/export.py
whirr/cli/init_cmd.py
whirr/cli/logs.py
whirr/cli/main.py
whirr/cli/retry.py
whirr/cli/runs.py
whirr/cli/server_cmd.py
whirr/cli/status.py
whirr/cli/submit.py
whirr/cli/sweep.py
whirr/cli/watch.py
whirr/cli/worker.py
whirr/cli/ablate/__init__.py
whirr/cli/ablate/add.py
whirr/cli/ablate/init_cmd.py
whirr/cli/ablate/rank.py
whirr/cli/ablate/run.py
whirr/dashboard/__init__.py
whirr/dashboard/server.py
whirr/dashboard/templates/base.html
whirr/dashboard/templates/index.html
whirr/dashboard/templates/queue.html
whirr/dashboard/templates/run_detail.html
whirr/dashboard/templates/runs.html
whirr/dashboard/templates/partials/jobs.html
whirr/dashboard/templates/partials/recent_runs.html
whirr/dashboard/templates/partials/stats.html
whirr/dashboard/templates/partials/workers.html
whirr/models/__init__.py
whirr/models/ablation.py
whirr/models/api.py
whirr/models/base.py
whirr/models/db.py
whirr/models/run.py
whirr/server/__init__.py
whirr/server/app.py
whirr/server/models.py
whirr-0.5.3.dist-info/METADATA
whirr-0.5.3.dist-info/WHEEL
whirr-0.5.3.dist-info/entry_points.txt
whirr-0.5.3.dist-info/licenses/LICENSE
whirr-0.5.3.dist-info/RECORD
