Metadata-Version: 2.4
Name: whirr
Version: 0.5.3
Summary: Local experiment orchestration. Queue jobs, track metrics, wake up to results.
Project-URL: Homepage, https://github.com/syntropy-systems-oss/whirr
Project-URL: Repository, https://github.com/syntropy-systems-oss/whirr
Project-URL: Issues, https://github.com/syntropy-systems-oss/whirr/issues
Author: Syntropy Systems
License-Expression: MIT
License-File: LICENSE
Keywords: experiment,ml,mlflow,orchestration,tracking,wandb
Classifier: Development Status :: 3 - Alpha
Classifier: Intended Audience :: Developers
Classifier: Intended Audience :: Science/Research
Classifier: License :: OSI Approved :: MIT License
Classifier: Programming Language :: Python :: 3
Classifier: Programming Language :: Python :: 3.9
Classifier: Programming Language :: Python :: 3.10
Classifier: Programming Language :: Python :: 3.11
Classifier: Programming Language :: Python :: 3.12
Classifier: Topic :: Scientific/Engineering :: Artificial Intelligence
Requires-Python: >=3.9
Requires-Dist: pydantic>=2.0
Requires-Dist: pyyaml>=6.0
Requires-Dist: rich>=13.0
Requires-Dist: typer>=0.9.0
Provides-Extra: ablate
Provides-Extra: dashboard
Requires-Dist: fastapi>=0.109.0; extra == 'dashboard'
Requires-Dist: jinja2>=3.1.0; extra == 'dashboard'
Requires-Dist: uvicorn>=0.27.0; extra == 'dashboard'
Provides-Extra: dev
Requires-Dist: fastapi>=0.109.0; extra == 'dev'
Requires-Dist: httpx>=0.25.0; extra == 'dev'
Requires-Dist: jinja2>=3.1.0; extra == 'dev'
Requires-Dist: psutil>=5.9; extra == 'dev'
Requires-Dist: psycopg2-binary>=2.9.0; extra == 'dev'
Requires-Dist: pytest-timeout>=2.0; extra == 'dev'
Requires-Dist: pytest>=7.0; extra == 'dev'
Requires-Dist: uvicorn>=0.27.0; extra == 'dev'
Provides-Extra: metrics
Requires-Dist: psutil>=5.9; extra == 'metrics'
Provides-Extra: server
Requires-Dist: fastapi>=0.109.0; extra == 'server'
Requires-Dist: httpx>=0.25.0; extra == 'server'
Requires-Dist: jinja2>=3.1.0; extra == 'server'
Requires-Dist: psycopg2-binary>=2.9.0; extra == 'server'
Requires-Dist: uvicorn>=0.27.0; extra == 'server'
